{"Item":{"__typename":{"S":"Report"},"companyID":{"S":"SCC"},"createdAt":{"S":"2021-03-15T01:02:24.448Z"},"date":{"S":"2021-03-12"},"referencer":{"L":[{"S":"ahoshikawa@sisco-consulting.co.jp"},{"S":"ananbu@sisco-consulting.co.jp"},{"S":"ematsuyama@sisco-consulting.co.jp"},{"S":"eyamada@sisco-consulting.co.jp"},{"S":"fkaneko@sisco-consulting.co.jp"},{"S":"hango@sisco-consulting.co.jp"},{"S":"hchiba@sisco-consulting.co.jp"},{"S":"hishii@sisco-consulting.co.jp"},{"S":"hkinjo@sisco-consulting.co.jp"},{"S":"itoshu@sisco-consulting.co.jp"},{"S":"jseno@sisco-consulting.co.jp"},{"S":"khanashiro@sisco-consulting.co.jp"},{"S":"kishida@sisco-consulting.co.jp"},{"S":"kumeda@sisco-consulting.co.jp"},{"S":"kyoshino@sisco-consulting.co.jp"},{"S":"mishii@sisco-consulting.co.jp"},{"S":"miyawaki@sisco-consulting.co.jp"},{"S":"ninoba@sisco-consulting.co.jp"},{"S":"nmatsuura@sisco-consulting.co.jp"},{"S":"ooi@sisco-consulting.co.jp"},{"S":"smikoda@sisco-consulting.co.jp"},{"S":"tiwata@sisco-consulting.co.jp"},{"S":"tkawashima@sisco-consulting.co.jp"},{"S":"tkinoshi@sisco-consulting.co.jp"},{"S":"tkobayashi@sisco-consulting.co.jp"},{"S":"tnaito@sisco-consulting.co.jp"},{"S":"tnemoto@sisco-consulting.co.jp"},{"S":"twatanabe@sisco-consulting.co.jp"},{"S":"tyamamoto@sisco-consulting.co.jp"},{"S":"xiangyi@sisco-consulting.co.jp"},{"S":"yando@sisco-consulting.co.jp"},{"S":"yhamazaki@sisco-consulting.co.jp"},{"S":"yhanada@sisco-consulting.co.jp"},{"S":"ykanai@sisco-consulting.co.jp"},{"S":"ysako@sisco-consulting.co.jp"},{"S":"yshimada@sisco-consulting.co.jp"},{"S":"yyomogida@sisco-consulting.co.jp"}]},"reviewee":{"S":"yando@sisco-consulting.co.jp"},"revieweeComments":{"M":{"other":{"S":""},"status":{"S":"①DX0492はクローズしDX0876へ継承、DX0876対応は担当者確認事項有りのため一部改修を次週持越し\n②ほかの方へ対応引継ぎ\n③対応完了、クローズ済み"},"work":{"S":"【2021/3/8~3/12作業内容】\n①2021/3/8~3/12：Step3受入障害対応 トータルピック実績更新 DX0492、DX0876\n②2021/3/8：Step3障害調査 トータルピック入力  DX0766\n③2021/3/9~3/10：Step3内結障害対応 出荷先マスタデータ取込 DX0783 → 設計書不良による差し戻し分の改修\n"}}},"reviewer":{"L":[{"S":"nmatsuura@sisco-consulting.co.jp"}]},"sub":{"S":"17148230-6876-49ab-b41b-c7ac4b0a38d6"},"updatedAt":{"S":"2021-04-22T07:40:13.771Z"},"workStatus":{"S":"InTask"}}}
{"Item":{"__typename":{"S":"Report"},"companyID":{"S":"SCC"},"createdAt":{"S":"2021-03-29T10:13:38.466Z"},"date":{"S":"2021-03-26"},"referencer":{"L":[{"S":"ahoshikawa@sisco-consulting.co.jp"},{"S":"ananbu@sisco-consulting.co.jp"},{"S":"ematsuyama@sisco-consulting.co.jp"},{"S":"eyamada@sisco-consulting.co.jp"},{"S":"fkaneko@sisco-consulting.co.jp"},{"S":"hango@sisco-consulting.co.jp"},{"S":"hchiba@sisco-consulting.co.jp"},{"S":"hishii@sisco-consulting.co.jp"},{"S":"hkinjo@sisco-consulting.co.jp"},{"S":"itoshu@sisco-consulting.co.jp"},{"S":"jseno@sisco-consulting.co.jp"},{"S":"khanashiro@sisco-consulting.co.jp"},{"S":"kishida@sisco-consulting.co.jp"},{"S":"kumeda@sisco-consulting.co.jp"},{"S":"kyoshino@sisco-consulting.co.jp"},{"S":"mishii@sisco-consulting.co.jp"},{"S":"miyawaki@sisco-consulting.co.jp"},{"S":"ninoba@sisco-consulting.co.jp"},{"S":"nmatsuura@sisco-consulting.co.jp"},{"S":"ooi@sisco-consulting.co.jp"},{"S":"smikoda@sisco-consulting.co.jp"},{"S":"tiwata@sisco-consulting.co.jp"},{"S":"tkawashima@sisco-consulting.co.jp"},{"S":"tkinoshi@sisco-consulting.co.jp"},{"S":"tkobayashi@sisco-consulting.co.jp"},{"S":"tnaito@sisco-consulting.co.jp"},{"S":"tnemoto@sisco-consulting.co.jp"},{"S":"twatanabe@sisco-consulting.co.jp"},{"S":"tyamamoto@sisco-consulting.co.jp"},{"S":"xiangyi@sisco-consulting.co.jp"},{"S":"yando@sisco-consulting.co.jp"},{"S":"yhamazaki@sisco-consulting.co.jp"},{"S":"yhanada@sisco-consulting.co.jp"},{"S":"ykanai@sisco-consulting.co.jp"},{"S":"ysako@sisco-consulting.co.jp"},{"S":"yshimada@sisco-consulting.co.jp"},{"S":"yyomogida@sisco-consulting.co.jp"}]},"reviewee":{"S":"yando@sisco-consulting.co.jp"},"revieweeComments":{"M":{"other":{"S":""},"status":{"S":""},"work":{"S":"【2021/3/22～26　作業内容】\n・Step3　仕様変更対応：商品マスタデータ取込、商品マスタメンテ\n・Step3　操作手順書作成：既存修正2件、新規8件"}}},"reviewer":{"L":[{"S":"nmatsuura@sisco-consulting.co.jp"}]},"sub":{"S":"17148230-6876-49ab-b41b-c7ac4b0a38d6"},"updatedAt":{"S":"2021-04-22T07:40:13.725Z"},"workStatus":{"S":"OK"}}}
{"Item":{"__typename":{"S":"Report"},"companyID":{"S":"SCC"},"createdAt":{"S":"2021-04-19T09:38:57.896Z"},"date":{"S":"2021-04-16"},"referencer":{"L":[{"S":"ahoshikawa@sisco-consulting.co.jp"},{"S":"ananbu@sisco-consulting.co.jp"},{"S":"ematsuyama@sisco-consulting.co.jp"},{"S":"eyamada@sisco-consulting.co.jp"},{"S":"fkaneko@sisco-consulting.co.jp"},{"S":"hango@sisco-consulting.co.jp"},{"S":"hchiba@sisco-consulting.co.jp"},{"S":"hishii@sisco-consulting.co.jp"},{"S":"hkinjo@sisco-consulting.co.jp"},{"S":"itoshu@sisco-consulting.co.jp"},{"S":"jseno@sisco-consulting.co.jp"},{"S":"khanashiro@sisco-consulting.co.jp"},{"S":"kishida@sisco-consulting.co.jp"},{"S":"kumeda@sisco-consulting.co.jp"},{"S":"kyoshino@sisco-consulting.co.jp"},{"S":"mishii@sisco-consulting.co.jp"},{"S":"miyawaki@sisco-consulting.co.jp"},{"S":"ninoba@sisco-consulting.co.jp"},{"S":"nmatsuura@sisco-consulting.co.jp"},{"S":"ooi@sisco-consulting.co.jp"},{"S":"smikoda@sisco-consulting.co.jp"},{"S":"tiwata@sisco-consulting.co.jp"},{"S":"tkawashima@sisco-consulting.co.jp"},{"S":"tkinoshi@sisco-consulting.co.jp"},{"S":"tkobayashi@sisco-consulting.co.jp"},{"S":"tnaito@sisco-consulting.co.jp"},{"S":"tnemoto@sisco-consulting.co.jp"},{"S":"twatanabe@sisco-consulting.co.jp"},{"S":"tyamamoto@sisco-consulting.co.jp"},{"S":"xiangyi@sisco-consulting.co.jp"},{"S":"yando@sisco-consulting.co.jp"},{"S":"yhamazaki@sisco-consulting.co.jp"},{"S":"yhanada@sisco-consulting.co.jp"},{"S":"ykanai@sisco-consulting.co.jp"},{"S":"ysako@sisco-consulting.co.jp"},{"S":"yshimada@sisco-consulting.co.jp"},{"S":"yyomogida@sisco-consulting.co.jp"}]},"reviewee":{"S":"yando@sisco-consulting.co.jp"},"revieweeComments":{"M":{"other":{"S":""},"status":{"S":"今週で任された作業はすべて完了済み。"},"work":{"S":"【2021/4/12～16　作業内容】\n・Step3詳細設計書_STEP2-2障害修正取込の調査\n・システム制御項目の最新化\n・Step3納品準備：操作手順書：ハードコピー最新版取得対象機能調査、ハードコピー貼替、改訂日変更等整形\n・Step3納品準備：詳細設計書：改訂履歴変更、Step3対象外機能最終整形"}}},"reviewer":{"L":[{"S":"nmatsuura@sisco-consulting.co.jp"}]},"sub":{"S":"17148230-6876-49ab-b41b-c7ac4b0a38d6"},"updatedAt":{"S":"2021-04-22T07:40:13.719Z"},"workStatus":{"S":"OK"}}}
{"Item":{"__typename":{"S":"Report"},"companyID":{"S":"SCC"},"createdAt":{"S":"2021-04-09T09:51:12.298Z"},"date":{"S":"2021-04-09"},"referencer":{"L":[{"S":"ahoshikawa@sisco-consulting.co.jp"},{"S":"ananbu@sisco-consulting.co.jp"},{"S":"ematsuyama@sisco-consulting.co.jp"},{"S":"eyamada@sisco-consulting.co.jp"},{"S":"fkaneko@sisco-consulting.co.jp"},{"S":"hango@sisco-consulting.co.jp"},{"S":"hchiba@sisco-consulting.co.jp"},{"S":"hishii@sisco-consulting.co.jp"},{"S":"hkinjo@sisco-consulting.co.jp"},{"S":"itoshu@sisco-consulting.co.jp"},{"S":"jseno@sisco-consulting.co.jp"},{"S":"khanashiro@sisco-consulting.co.jp"},{"S":"kishida@sisco-consulting.co.jp"},{"S":"kumeda@sisco-consulting.co.jp"},{"S":"kyoshino@sisco-consulting.co.jp"},{"S":"mishii@sisco-consulting.co.jp"},{"S":"miyawaki@sisco-consulting.co.jp"},{"S":"ninoba@sisco-consulting.co.jp"},{"S":"nmatsuura@sisco-consulting.co.jp"},{"S":"ooi@sisco-consulting.co.jp"},{"S":"smikoda@sisco-consulting.co.jp"},{"S":"tiwata@sisco-consulting.co.jp"},{"S":"tkawashima@sisco-consulting.co.jp"},{"S":"tkinoshi@sisco-consulting.co.jp"},{"S":"tkobayashi@sisco-consulting.co.jp"},{"S":"tnaito@sisco-consulting.co.jp"},{"S":"tnemoto@sisco-consulting.co.jp"},{"S":"twatanabe@sisco-consulting.co.jp"},{"S":"tyamamoto@sisco-consulting.co.jp"},{"S":"xiangyi@sisco-consulting.co.jp"},{"S":"yando@sisco-consulting.co.jp"},{"S":"yhamazaki@sisco-consulting.co.jp"},{"S":"yhanada@sisco-consulting.co.jp"},{"S":"ykanai@sisco-consulting.co.jp"},{"S":"ysako@sisco-consulting.co.jp"},{"S":"yshimada@sisco-consulting.co.jp"},{"S":"yyomogida@sisco-consulting.co.jp"}]},"reviewee":{"S":"yando@sisco-consulting.co.jp"},"revieweeComments":{"M":{"other":{"S":""},"status":{"S":"今週作業はドキュメント作業中心であり、お客様と作業状況の報告や問題共有しつつ問題なく進められている。"},"work":{"S":"【2021/4/5～4/9　作業内容】\n・Step3操作手順書(HT）新規1件\n・Step3操作手順書 管理台帳の整理\n・詳細設計書の目次(画面／HT)最新化\n・DB物理設計書の修正\n・帳票一覧の作成\n・機能一覧の作成\n・インターフェース一覧の作成\n・詳細設計書の全量準備\n・STEP2-2障害修正取込の調査"}}},"reviewer":{"L":[{"S":"nmatsuura@sisco-consulting.co.jp"}]},"sub":{"S":"17148230-6876-49ab-b41b-c7ac4b0a38d6"},"updatedAt":{"S":"2021-04-22T07:40:13.830Z"},"workStatus":{"S":"OK"}}}
{"Item":{"__typename":{"S":"Report"},"companyID":{"S":"SCC"},"createdAt":{"S":"2021-03-24T09:47:56.893Z"},"date":{"S":"2021-03-19"},"referencer":{"L":[{"S":"ahoshikawa@sisco-consulting.co.jp"},{"S":"ananbu@sisco-consulting.co.jp"},{"S":"ematsuyama@sisco-consulting.co.jp"},{"S":"eyamada@sisco-consulting.co.jp"},{"S":"fkaneko@sisco-consulting.co.jp"},{"S":"hango@sisco-consulting.co.jp"},{"S":"hchiba@sisco-consulting.co.jp"},{"S":"hishii@sisco-consulting.co.jp"},{"S":"hkinjo@sisco-consulting.co.jp"},{"S":"itoshu@sisco-consulting.co.jp"},{"S":"jseno@sisco-consulting.co.jp"},{"S":"khanashiro@sisco-consulting.co.jp"},{"S":"kishida@sisco-consulting.co.jp"},{"S":"kumeda@sisco-consulting.co.jp"},{"S":"kyoshino@sisco-consulting.co.jp"},{"S":"mishii@sisco-consulting.co.jp"},{"S":"miyawaki@sisco-consulting.co.jp"},{"S":"ninoba@sisco-consulting.co.jp"},{"S":"nmatsuura@sisco-consulting.co.jp"},{"S":"ooi@sisco-consulting.co.jp"},{"S":"smikoda@sisco-consulting.co.jp"},{"S":"tiwata@sisco-consulting.co.jp"},{"S":"tkawashima@sisco-consulting.co.jp"},{"S":"tkinoshi@sisco-consulting.co.jp"},{"S":"tkobayashi@sisco-consulting.co.jp"},{"S":"tnaito@sisco-consulting.co.jp"},{"S":"tnemoto@sisco-consulting.co.jp"},{"S":"twatanabe@sisco-consulting.co.jp"},{"S":"tyamamoto@sisco-consulting.co.jp"},{"S":"xiangyi@sisco-consulting.co.jp"},{"S":"yando@sisco-consulting.co.jp"},{"S":"yhamazaki@sisco-consulting.co.jp"},{"S":"yhanada@sisco-consulting.co.jp"},{"S":"ykanai@sisco-consulting.co.jp"},{"S":"ysako@sisco-consulting.co.jp"},{"S":"yshimada@sisco-consulting.co.jp"},{"S":"yyomogida@sisco-consulting.co.jp"}]},"reviewee":{"S":"yando@sisco-consulting.co.jp"},"revieweeComments":{"M":{"other":{"S":""},"status":{"S":""},"work":{"S":"【2021/3/15～19　作業内容】\n①2021/3/15,19：Step3受入障害対応 トータルピック実績更新　DX0876\n②2021/3/19：Step3内結障害対応　トータルピック入力\n③2021/3/15：受入試験項目数取得　作業\n④2021/3/16～19：Step3操作手順書作成　改修28件新規1件、管理台帳作成、改訂履歴修正"}}},"reviewer":{"L":[{"S":"nmatsuura@sisco-consulting.co.jp"}]},"sub":{"S":"17148230-6876-49ab-b41b-c7ac4b0a38d6"},"updatedAt":{"S":"2021-04-22T07:40:13.470Z"},"workStatus":{"S":"OK"}}}
{"Item":{"__typename":{"S":"Report"},"companyID":{"S":"SCC"},"createdAt":{"S":"2021-03-25T07:10:59.063Z"},"date":{"S":"2021-03-10"},"referencer":{"L":[{"S":"ahoshikawa@sisco-consulting.co.jp"},{"S":"ananbu@sisco-consulting.co.jp"},{"S":"ematsuyama@sisco-consulting.co.jp"},{"S":"eyamada@sisco-consulting.co.jp"},{"S":"fkaneko@sisco-consulting.co.jp"},{"S":"hango@sisco-consulting.co.jp"},{"S":"hchiba@sisco-consulting.co.jp"},{"S":"hishii@sisco-consulting.co.jp"},{"S":"hkinjo@sisco-consulting.co.jp"},{"S":"itoshu@sisco-consulting.co.jp"},{"S":"jseno@sisco-consulting.co.jp"},{"S":"khanashiro@sisco-consulting.co.jp"},{"S":"kishida@sisco-consulting.co.jp"},{"S":"kumeda@sisco-consulting.co.jp"},{"S":"kyoshino@sisco-consulting.co.jp"},{"S":"mishii@sisco-consulting.co.jp"},{"S":"miyawaki@sisco-consulting.co.jp"},{"S":"ninoba@sisco-consulting.co.jp"},{"S":"nmatsuura@sisco-consulting.co.jp"},{"S":"ooi@sisco-consulting.co.jp"},{"S":"smikoda@sisco-consulting.co.jp"},{"S":"tiwata@sisco-consulting.co.jp"},{"S":"tkawashima@sisco-consulting.co.jp"},{"S":"tkinoshi@sisco-consulting.co.jp"},{"S":"tkobayashi@sisco-consulting.co.jp"},{"S":"tnaito@sisco-consulting.co.jp"},{"S":"tnemoto@sisco-consulting.co.jp"},{"S":"twatanabe@sisco-consulting.co.jp"},{"S":"tyamamoto@sisco-consulting.co.jp"},{"S":"xiangyi@sisco-consulting.co.jp"},{"S":"yando@sisco-consulting.co.jp"},{"S":"yhamazaki@sisco-consulting.co.jp"},{"S":"yhanada@sisco-consulting.co.jp"},{"S":"ykanai@sisco-consulting.co.jp"},{"S":"ysako@sisco-consulting.co.jp"},{"S":"yshimada@sisco-consulting.co.jp"},{"S":"yyomogida@sisco-consulting.co.jp"}]},"reviewee":{"S":"hango@sisco-consulting.co.jp"},"revieweeComments":{"M":{"other":{"S":""},"status":{"S":"既存会社案内の内容を直す\n時間かかかったが、"},"work":{"S":"会社案内を新しい作る"}}},"reviewer":{"L":[{"S":"tkawashima@sisco-consulting.co.jp"}]},"sub":{"S":"fbed6e2a-2067-4eaa-9547-7ea9f6911233"},"updatedAt":{"S":"2021-04-22T07:40:13.408Z"},"workStatus":{"S":"InTask"}}}
{"Item":{"__typename":{"S":"Report"},"companyID":{"S":"SCC"},"createdAt":{"S":"2021-04-22T08:26:40.218Z"},"date":{"S":"2021-04-22"},"referencer":{"L":[{"S":"ahoshikawa@sisco-consulting.co.jp"},{"S":"ananbu@sisco-consulting.co.jp"},{"S":"ematsuyama@sisco-consulting.co.jp"},{"S":"eyamada@sisco-consulting.co.jp"},{"S":"fkaneko@sisco-consulting.co.jp"},{"S":"hango@sisco-consulting.co.jp"},{"S":"hchiba@sisco-consulting.co.jp"},{"S":"hishii@sisco-consulting.co.jp"},{"S":"hkinjo@sisco-consulting.co.jp"},{"S":"itoshu@sisco-consulting.co.jp"},{"S":"jseno@sisco-consulting.co.jp"},{"S":"khanashiro@sisco-consulting.co.jp"},{"S":"kishida@sisco-consulting.co.jp"},{"S":"kumeda@sisco-consulting.co.jp"},{"S":"kyoshino@sisco-consulting.co.jp"},{"S":"mishii@sisco-consulting.co.jp"},{"S":"miyawaki@sisco-consulting.co.jp"},{"S":"ninoba@sisco-consulting.co.jp"},{"S":"nmatsuura@sisco-consulting.co.jp"},{"S":"ooi@sisco-consulting.co.jp"},{"S":"smikoda@sisco-consulting.co.jp"},{"S":"tiwata@sisco-consulting.co.jp"},{"S":"tkawashima@sisco-consulting.co.jp"},{"S":"tkinoshi@sisco-consulting.co.jp"},{"S":"tkobayashi@sisco-consulting.co.jp"},{"S":"tnaito@sisco-consulting.co.jp"},{"S":"tnemoto@sisco-consulting.co.jp"},{"S":"twatanabe@sisco-consulting.co.jp"},{"S":"tyamamoto@sisco-consulting.co.jp"},{"S":"xiangyi@sisco-consulting.co.jp"},{"S":"yando@sisco-consulting.co.jp"},{"S":"yhamazaki@sisco-consulting.co.jp"},{"S":"yhanada@sisco-consulting.co.jp"},{"S":"ykanai@sisco-consulting.co.jp"},{"S":"ysako@sisco-consulting.co.jp"},{"S":"yshimada@sisco-consulting.co.jp"},{"S":"yyomogida@sisco-consulting.co.jp"}]},"reviewee":{"S":"hango@sisco-consulting.co.jp"},"revieweeComments":{"M":{"other":{"S":""},"status":{"S":"①現在ORCの件は優先順位ではないので、多々提案してもまだ使わない\n②値段の問題ではなくて、現在会社は他の事も考えないといけない事もある\n③新しい事を導入する前に、時間がかかる、他の部門も一緒に同意しないといけない\n④最後、領収書の件はボリュームがあるがまだ対応可能状況\n"},"work":{"S":"エス・シーアライアンスの石田さんに電話で連絡しました。\nOCRの見送りの理由を教えて頂けませんでしょうかという質問しました。\n石田さんの答えは：\n"}}},"reviewer":{"L":[{"S":"tkawashima@sisco-consulting.co.jp"}]},"sub":{"S":"fbed6e2a-2067-4eaa-9547-7ea9f6911233"},"updatedAt":{"S":"2021-04-22T08:26:40.218Z"},"workStatus":{"S":"InTask"}}}
{"Item":{"__typename":{"S":"Report"},"companyID":{"S":"SCC"},"createdAt":{"S":"2021-04-06T09:09:02.052Z"},"date":{"S":"2021-04-02"},"referencer":{"L":[{"S":"ahoshikawa@sisco-consulting.co.jp"},{"S":"ananbu@sisco-consulting.co.jp"},{"S":"ematsuyama@sisco-consulting.co.jp"},{"S":"eyamada@sisco-consulting.co.jp"},{"S":"fkaneko@sisco-consulting.co.jp"},{"S":"hango@sisco-consulting.co.jp"},{"S":"hchiba@sisco-consulting.co.jp"},{"S":"hishii@sisco-consulting.co.jp"},{"S":"hkinjo@sisco-consulting.co.jp"},{"S":"itoshu@sisco-consulting.co.jp"},{"S":"jseno@sisco-consulting.co.jp"},{"S":"khanashiro@sisco-consulting.co.jp"},{"S":"kishida@sisco-consulting.co.jp"},{"S":"kumeda@sisco-consulting.co.jp"},{"S":"kyoshino@sisco-consulting.co.jp"},{"S":"mishii@sisco-consulting.co.jp"},{"S":"miyawaki@sisco-consulting.co.jp"},{"S":"ninoba@sisco-consulting.co.jp"},{"S":"nmatsuura@sisco-consulting.co.jp"},{"S":"ooi@sisco-consulting.co.jp"},{"S":"smikoda@sisco-consulting.co.jp"},{"S":"tiwata@sisco-consulting.co.jp"},{"S":"tkawashima@sisco-consulting.co.jp"},{"S":"tkinoshi@sisco-consulting.co.jp"},{"S":"tkobayashi@sisco-consulting.co.jp"},{"S":"tnaito@sisco-consulting.co.jp"},{"S":"tnemoto@sisco-consulting.co.jp"},{"S":"twatanabe@sisco-consulting.co.jp"},{"S":"tyamamoto@sisco-consulting.co.jp"},{"S":"xiangyi@sisco-consulting.co.jp"},{"S":"yando@sisco-consulting.co.jp"},{"S":"yhamazaki@sisco-consulting.co.jp"},{"S":"yhanada@sisco-consulting.co.jp"},{"S":"ykanai@sisco-consulting.co.jp"},{"S":"ysako@sisco-consulting.co.jp"},{"S":"yshimada@sisco-consulting.co.jp"},{"S":"yyomogida@sisco-consulting.co.jp"}]},"reviewee":{"S":"yando@sisco-consulting.co.jp"},"revieweeComments":{"M":{"other":{"S":""},"status":{"S":""},"work":{"S":"【2021/3/29~4/2　作業内容】\n・Step3操作手順書作成,記述修正等整形：Web,HT,CL　10件"}}},"reviewer":{"L":[{"S":"nmatsuura@sisco-consulting.co.jp"}]},"sub":{"S":"17148230-6876-49ab-b41b-c7ac4b0a38d6"},"updatedAt":{"S":"2021-04-22T07:40:13.841Z"},"workStatus":{"S":"OK"}}}
{"Item":{"__typename":{"S":"Report"},"companyID":{"S":"SCC"},"createdAt":{"S":"2021-03-25T07:09:12.650Z"},"date":{"S":"2021-03-09"},"referencer":{"L":[{"S":"ahoshikawa@sisco-consulting.co.jp"},{"S":"ananbu@sisco-consulting.co.jp"},{"S":"ematsuyama@sisco-consulting.co.jp"},{"S":"eyamada@sisco-consulting.co.jp"},{"S":"fkaneko@sisco-consulting.co.jp"},{"S":"hango@sisco-consulting.co.jp"},{"S":"hchiba@sisco-consulting.co.jp"},{"S":"hishii@sisco-consulting.co.jp"},{"S":"hkinjo@sisco-consulting.co.jp"},{"S":"itoshu@sisco-consulting.co.jp"},{"S":"jseno@sisco-consulting.co.jp"},{"S":"khanashiro@sisco-consulting.co.jp"},{"S":"kishida@sisco-consulting.co.jp"},{"S":"kumeda@sisco-consulting.co.jp"},{"S":"kyoshino@sisco-consulting.co.jp"},{"S":"mishii@sisco-consulting.co.jp"},{"S":"miyawaki@sisco-consulting.co.jp"},{"S":"ninoba@sisco-consulting.co.jp"},{"S":"nmatsuura@sisco-consulting.co.jp"},{"S":"ooi@sisco-consulting.co.jp"},{"S":"smikoda@sisco-consulting.co.jp"},{"S":"tiwata@sisco-consulting.co.jp"},{"S":"tkawashima@sisco-consulting.co.jp"},{"S":"tkinoshi@sisco-consulting.co.jp"},{"S":"tkobayashi@sisco-consulting.co.jp"},{"S":"tnaito@sisco-consulting.co.jp"},{"S":"tnemoto@sisco-consulting.co.jp"},{"S":"twatanabe@sisco-consulting.co.jp"},{"S":"tyamamoto@sisco-consulting.co.jp"},{"S":"xiangyi@sisco-consulting.co.jp"},{"S":"yando@sisco-consulting.co.jp"},{"S":"yhamazaki@sisco-consulting.co.jp"},{"S":"yhanada@sisco-consulting.co.jp"},{"S":"ykanai@sisco-consulting.co.jp"},{"S":"ysako@sisco-consulting.co.jp"},{"S":"yshimada@sisco-consulting.co.jp"},{"S":"yyomogida@sisco-consulting.co.jp"}]},"reviewee":{"S":"hango@sisco-consulting.co.jp"},"revieweeComments":{"M":{"other":{"S":""},"status":{"S":"メールでトラブルがあったん\n日本語がおかしかった\nｔひ"},"work":{"S":"ABCさんとメールでやり取り\nは"}}},"reviewer":{"L":[{"S":"tkawashima@sisco-consulting.co.jp"}]},"sub":{"S":"fbed6e2a-2067-4eaa-9547-7ea9f6911233"},"updatedAt":{"S":"2021-04-22T07:40:13.400Z"},"workStatus":{"S":"OK"}}}
